{"result":"ok","tuc":[{"phrase":{"text":"flatter","language":"en"},"meanings":[{"language":"en","text":"To flatter in an obsequious manner."},{"language":"en","text":"to compliment someone"},{"language":"en","text":"to enhance someone&#39;s vanity"},{"language":"es","text":"Elogiar de manera excesiva."}],"meaningId":-7658888628108378394,"authors":[70195]},{"phrase":{"text":"adulate","language":"en"},"meanings":[{"language":"en","text":"To flatter in an obsequious manner."},{"language":"es","text":"Elogiar de manera excesiva."}],"meaningId":-2542003041195972016,"authors":[2903]},{"phrase":{"text":"fawn","language":"en"},"meaningId":-6937839952795246831,"authors":[84595]},{"phrase":{"text":"butter up","language":"en"},"meaningId":7618301559381445344,"authors":[25018]},{"phrase":{"text":"compliment","language":"en"},"meaningId":903346815330484315,"authors":[25018]},{"phrase":{"text":"cringe","language":"en"},"meaningId":-578412477915210066,"authors":[25018]},{"phrase":{"text":"lick","language":"en"},"meaningId":-165878584841645161,"authors":[25018]},{"phrase":{"text":"blandish","language":"en"},"meanings":[{"language":"en","text":"To flatter in an obsequious manner."},{"language":"es","text":"Elogiar de manera excesiva."}],"meaningId":7697579348423641483,"authors":[60172]},{"phrase":{"text":"blarney","language":"en"},"meanings":[{"language":"en","text":"To flatter in an obsequious manner."},{"language":"es","text":"Elogiar de manera excesiva."}],"meaningId":-843449606303133589,"authors":[60172]},{"phrase":{"text":"adular","language":"en"},"meaningId":-6550347771945180577,"authors":[80097]},{"phrase":{"text":"adularia","language":"en"},"meaningId":-7747793068842988297,"authors":[80097]},{"phrase":{"text":"coax","language":"en"},"meaningId":4464823527867222163,"authors":[83064]},{"phrase":{"text":"court","language":"en"},"meaningId":-3146682416290415749,"authors":[86934]},{"phrase":{"text":"creep","language":"en"},"meaningId":7072494298713787922,"authors":[83093]},{"phrase":{"text":"fawn on","language":"en"},"meaningId":-6607373556999482808,"authors":[25018]},{"phrase":{"text":"flatter(flati)","language":"en"},"meaningId":3373820971879686716,"authors":[8]},{"phrase":{"text":"gloze","language":"en"},"meaningId":-117402605475161268,"authors":[25018]},{"phrase":{"text":"make up to","language":"en"},"meaningId":-9017180310164164537,"authors":[25018]},{"phrase":{"text":"play up to","language":"en"},"meaningId":-7270276685157813547,"authors":[25018]},{"phrase":{"text":"toady","language":"en"},"meaningId":-5557072511631657781,"authors":[25115]},{"phrase":{"text":"truckle","language":"en"},"meaningId":-6996506289205526522,"authors":[83093]},{"meanings":[{"language":"en","text":"to flatter"}],"meaningId":3418592560533037677,"authors":[93107]}],"phrase":"adular","examples":[{"author":118293,"first":"La <strong class=\"keyword\">adularé</strong> con detalles pero sin dejar de ser modesto.","second":"<strong class=\"keyword\">Flatter her</strong> in little ways but be modest myself."},{"author":118293,"first":"Deja de <strong class=\"keyword\">adular</strong> tus musculos.","second":"Hit the shower<strong class=\"keyword\">,</strong> muscles."},{"author":31,"first":"Ni sobornar y ser sobornado,...... <strong class=\"keyword\">adular</strong> al rey y despreciar al ciudadano","second":"I would not want to bribe and be bribed... to <strong class=\"keyword\">fawn</strong> upon the king and kick the commoner"},{"author":118293,"first":"He tenido que <strong class=\"keyword\">adular</strong>, humillarme y hacer de bufón hasta que el mundo entero se reía de mí.","second":"I've had to <strong class=\"keyword\">fawn</strong> and <strong class=\"keyword\">toady</strong>, and make a mock of myself... till all I could hear was the world laughing at me."},{"author":118293,"first":"La mayoría de los hombres piensa que <strong class=\"keyword\">adular</strong> a una mujer es la manera de conseguirla.","second":"Most men think that <strong class=\"keyword\">complimenting</strong> a woman is the way to land her."},{"author":118293,"first":"Mejor deja de <strong class=\"keyword\">adular</strong>.","second":"You better stop <strong class=\"keyword\">flattering</strong>."},{"author":118293,"first":"Entonces sugeriría que la <strong class=\"keyword\">adularas</strong>.","second":"Then I would suggest cozying <strong class=\"keyword\">up</strong> to <strong class=\"keyword\">her</strong>."},{"author":31,"first":"<strong class=\"keyword\">Adular</strong> así a Sullivan","second":"<strong class=\"keyword\">You poring over</strong> Sullivan like that"},{"author":118293,"first":"¿Por qué se iba a <strong class=\"keyword\">adular</strong> a los pobres?","second":"Why should the poor be <strong class=\"keyword\">flattered</strong>?"},{"author":118293,"first":"Has tenido tiempo de <strong class=\"keyword\">adular</strong> a 20 editores de la ciudad.","second":"You've been gone long enough <strong class=\"keyword\">to soft</strong>-soap 20 city editors."},{"author":92475,"first":"El político de la oposición, Boris Nemtsov, dedujo que el “patriota” Timchenko dio la entrevista para <strong class=\"keyword\">adular</strong> a Putin en preparación de los recortes de los presupuestos del estado.","second":"Opposition politician Boris Nemtsov reasoned that the “patriot” Timchenko gave the interview to <strong class=\"keyword\">suck up</strong> to Putin in preparation for the next skimming of the state budget."},{"author":118293,"first":"Su trabajo es de proteger no de <strong class=\"keyword\">adular</strong>.","second":"Your job is to protect, not to <strong class=\"keyword\">flatter</strong>."},{"author":118293,"first":"Sólo para... <strong class=\"keyword\">adular</strong> a Nikki.","second":"Just to... <strong class=\"keyword\">cozy up</strong> to Nikki."},{"author":118293,"first":"Deje de <strong class=\"keyword\">adular</strong>.","second":"Stop <strong class=\"keyword\">flattering me</strong>."},{"author":118293,"first":"Cuando el negocio andaba mal yo también solía <strong class=\"keyword\">adular</strong> a los diseñadores.","second":"I used to <strong class=\"keyword\">butter</strong> up the designers, too, when business was bad."},{"author":118293,"first":"¡ Sé que sólo me queréis <strong class=\"keyword\">adular</strong>, así que dejadlo ya!","second":"I know you're just trying to button me <strong class=\"keyword\">up</strong>, don't give me that!"},{"author":31,"first":"Has aprendido a <strong class=\"keyword\">adular</strong>","second":"You' ve learnt how to <strong class=\"keyword\">flatter</strong>"},{"author":118293,"first":"Ni sobornar y ser sobornado, <strong class=\"keyword\">adular</strong> al rey y despreciar al ciudadano.","second":"I would not want to bribe and be bribed... to <strong class=\"keyword\">fawn</strong> upon the king and kick the commoner."},{"author":118293,"first":"Sabes <strong class=\"keyword\">adular</strong> a un hombre.","second":"You know <strong class=\"keyword\">how</strong> to <strong class=\"keyword\">flatter</strong> a guy."},{"author":118293,"first":"No me importaría pero he tenido que cruzar la planta de fábrica, sin mencionar que todo apesta a pintura, todo por <strong class=\"keyword\">adular</strong> a algunos de la familia real.","second":"I wouldn't mind but I've just had to cross the factory floor, not to mention the whole place reeks of paint, all for the sake of <strong class=\"keyword\">buttering up</strong> a few royals."},{"author":118293,"first":"No hace falta, Max, deja, sólo la vas a <strong class=\"keyword\">adular</strong>.","second":"It'll only go to her head."},{"author":31,"first":"Hay que saludar, sonreír para la foto, <strong class=\"keyword\">adular</strong>","second":"Meet and greet, press the flesh, butt- <strong class=\"keyword\">kiss</strong>"},{"author":118293,"first":"No me gusta <strong class=\"keyword\">adular</strong> a las personas.","second":"I don't like to talk <strong class=\"keyword\">up</strong> to people."},{"author":119739,"first":"En cambio, cuando una muchedumbre quiso tratar como dioses a Pablo y a Bernabé, estos se lo impidieron. (Hch 14:11-15.) De modo semejante, cuando un gobernante judío intentó <strong class=\"keyword\">adular</strong> a Jesús con el título de “Buen Maestro”, él lo corrigió en el acto, diciéndole: “¿Por qué me llamas bueno?","second":"(Ac 14:11-15) Also, when a Jewish ruler attempted application of the <strong class=\"keyword\">flattering</strong> title “Good Teacher” <strong class=\"keyword\">to</strong> Jesus Christ, Jesus instantly corrected him, saying: “Why do you call me good?"},{"author":118293,"first":"Consejero, si estás tratando de halagarme, primero debe <strong class=\"keyword\">adular</strong> a mi esposa.","second":"Counselor, if you're trying to flatter me, <strong class=\"keyword\">you</strong> must first woo my wife!"}],"from":"es","dest":"en","authors":{"80097":{"U":"http://www.btb.termiumplus.gc.ca/","id":80097,"N":"Termium","url":"https://glosbe.com/source/80097"},"8":{"U":"http://es.wiktionary.org","id":8,"N":"es.wiktionary.org","url":"https://glosbe.com/source/8"},"60172":{"U":"http://www.omegawiki.org/","id":60172,"N":"omegawiki","url":"https://glosbe.com/source/60172"},"70195":{"U":"","id":70195,"N":"en.wiktionary.org_2014","url":"https://glosbe.com/source/70195"},"84595":{"U":"","id":84595,"N":"i2e - English-Spanish Dictionary","url":"https://glosbe.com/source/84595"},"93107":{"U":"","id":93107,"N":"enwiki-01-2017-defs","url":"https://glosbe.com/source/93107"},"83093":{"U":"","id":83093,"N":"Dbnary: Wiktionary as Linguistic Linked Open Data","url":"https://glosbe.com/source/83093"},"118293":{"U":"https://www.opensubtitles.org/","id":118293,"N":"opensubtitles2017","url":"https://glosbe.com/source/118293"},"2903":{"U":"","id":2903,"N":"i2e-English-Spanish-Dictionary","url":"https://glosbe.com/source/2903"},"86934":{"U":"","id":86934,"N":"Glosbe Research","url":"https://glosbe.com/source/86934"},"83064":{"U":"","id":83064,"N":"Dbnary: Wiktionary as Linguistic Linked Open Data","url":"https://glosbe.com/source/83064"},"25018":{"U":"http://glosbe.com","id":25018,"N":"GlosbeResearch","url":"https://glosbe.com/source/25018"},"92475":{"U":"http://globalvoicesonline.org","id":92475,"N":"globalvoices","url":"https://glosbe.com/source/92475"},"119739":{"U":"","id":119739,"N":"JW_2017_12","url":"https://glosbe.com/source/119739"},"25115":{"U":"","id":25115,"N":"GlTrav3","url":"https://glosbe.com/source/25115"},"31":{"U":"http://www.opensubtitles.org/","id":31,"N":"opensubtitles2","url":"https://glosbe.com/source/31"}}}