{"result":"ok","tuc":[{"phrase":{"text":"aversion","language":"en"},"meanings":[{"language":"es","text":"Estado de detestar al extremo; sentimiento de desagrado total."},{"language":"en","text":"fixed dislike"},{"language":"en","text":"Extreme hatred or detestation; the feeling of utter dislike."}],"meaningId":-564236657330528278,"authors":[70195]},{"phrase":{"text":"dislike","language":"en"},"meanings":[{"language":"en","text":"A feeling of aversion or antipathy."},{"language":"en","text":"feeling of distaste"},{"language":"en","text":"not to like something"},{"language":"es","text":"Sentimiento de aversión o antipatía."}],"meaningId":-376389774008570874,"authors":[70195]},{"phrase":{"text":"loathing","language":"en"},"meaningId":4376209820757288598,"authors":[69425]},{"phrase":{"text":"abhorrence","language":"en"},"meanings":[{"language":"es","text":"Estado de detestar al extremo; sentimiento de desagrado total."},{"language":"en","text":"Extreme hatred or detestation; the feeling of utter dislike."}],"meaningId":8549948307638968780,"authors":[69425]},{"phrase":{"text":"antipathy","language":"en"},"meanings":[{"language":"en","text":"contrariety or opposition in feeling"}],"meaningId":-7413908780529461927,"authors":[70195]},{"phrase":{"text":"abomination","language":"en"},"meanings":[{"language":"es","text":"Estado de detestar al extremo; sentimiento de desagrado total."},{"language":"en","text":"Extreme hatred or detestation; the feeling of utter dislike."}],"meaningId":-2973629970028763836,"authors":[69425]},{"phrase":{"text":"disgust","language":"en"},"meanings":[{"language":"es","text":"Estado de detestar al extremo; sentimiento de desagrado total."},{"language":"en","text":"Extreme hatred or detestation; the feeling of utter dislike."}],"meaningId":-4140406083139004647,"authors":[69425]},{"phrase":{"text":"distaste","language":"en"},"meaningId":-6901104516676233423,"authors":[69425]},{"phrase":{"text":"detestation","language":"en"},"meanings":[{"language":"es","text":"Estado de detestar al extremo; sentimiento de desagrado total."},{"language":"en","text":"Extreme hatred or detestation; the feeling of utter dislike."}],"meaningId":-1198458660965008203,"authors":[84500]},{"phrase":{"text":"repugnance","language":"en"},"meaningId":-7223437903886109375,"authors":[9]},{"phrase":{"text":"disinclination","language":"en"},"meanings":[{"language":"en","text":"A certain degree of unwillingness."},{"language":"es","text":"Un cierto grado de falta de voluntad."}],"meaningId":6731245938017398105,"authors":[97745]},{"phrase":{"text":"hate","language":"en"},"meaningId":3716115494004783604,"authors":[25018]},{"phrase":{"text":"hatred","language":"en"},"meaningId":3981143088748976826,"authors":[84715]},{"phrase":{"text":"horror","language":"en"},"meaningId":-8101081604370177711,"authors":[1]},{"phrase":{"text":"repulsion","language":"en"},"meaningId":-8619820485913410536,"authors":[69425]},{"phrase":{"text":"revulsion","language":"en"},"meaningId":-1944189311073761033,"authors":[69425]},{"phrase":{"text":"hesitancy","language":"en"},"meanings":[{"language":"en","text":"A certain degree of unwillingness."},{"language":"es","text":"Un cierto grado de falta de voluntad."}],"meaningId":9113237880286520532,"authors":[60172]},{"phrase":{"text":"hesitation","language":"en"},"meanings":[{"language":"en","text":"A certain degree of unwillingness."},{"language":"es","text":"Un cierto grado de falta de voluntad."}],"meaningId":342928689866292527,"authors":[60172]},{"phrase":{"text":"indisposition","language":"en"},"meanings":[{"language":"en","text":"A certain degree of unwillingness."},{"language":"es","text":"Un cierto grado de falta de voluntad."}],"meaningId":-5238808722424342881,"authors":[60172]},{"phrase":{"text":"reluctance","language":"en"},"meanings":[{"language":"en","text":"A certain degree of unwillingness."},{"language":"es","text":"Un cierto grado de falta de voluntad."}],"meaningId":4321285922362332372,"authors":[60172]},{"phrase":{"text":"atrocity","language":"en"},"meaningId":-7540998657090720568,"authors":[2698]},{"phrase":{"text":"aversion therapy","language":"en"},"meaningId":2963932578829206762,"authors":[80097]},{"phrase":{"text":"aversive therapy","language":"en"},"meaningId":6343902064786117127,"authors":[80097]},{"phrase":{"text":"dislike(antipatio)","language":"en"},"meaningId":-4256487979632786951,"authors":[8]},{"phrase":{"text":"distastefulness","language":"en"},"meaningId":-4883787239996742244,"authors":[97745]},{"phrase":{"text":"execration","language":"en"},"meaningId":3191728451152191773,"authors":[84500]},{"phrase":{"text":"horror(abomeno)","language":"en"},"meaningId":-7257914002250251931,"authors":[8]},{"phrase":{"text":"nausea","language":"en"},"meaningId":5515837302224823553,"authors":[36]},{"phrase":{"text":"nausea(naŭzo)","language":"en"},"meaningId":5954385268189753410,"authors":[8]},{"phrase":{"text":"odium","language":"en"},"meaningId":1917166659377740063,"authors":[84500]},{"meanings":[{"language":"en","text":"aversion"}],"meaningId":7613979374893990648,"authors":[1]}],"phrase":"aversión","examples":[{"author":94808,"first":"Aunque la actitud real de estos extremistas de derecha hacia los árabes, palestinos y musulmanes no se refleje en su apoyo verbal, la intensidad de sus sentimientos antijudíos parece superar su <strong class=\"keyword\">aversión</strong> racista y xenófoba de los árabes y musulmanes.","second":"While the real attitude of these right extremists toward Arabs, Palestinians and Muslims may not be reflected in their verbal support for them, the intensity of their anti-Jewish feelings appear to overcome their racist and xenophobic <strong class=\"keyword\">aversion</strong> to Arabs and Muslims."},{"author":94809,"first":"a) respuestas de comportamiento tras la captura, incluyendo vocalizaciones, pánico extremo y <strong class=\"keyword\">aversión</strong>.","second":"(a) behavioural responses after trapping, including vocalizations, extreme panic, delay before return to normal behaviour after release from <strong class=\"keyword\">trap</strong> and <strong class=\"keyword\">aversiveness</strong>."},{"author":94809,"first":"La <strong class=\"keyword\">aversión</strong> podrá evaluarse capturando al animal en una situación fácilmente reconocible, y luego volviéndolo a exponer a la trampa en la situación adecuada y evaluando su comportamiento.","second":"<strong class=\"keyword\">Aversiveness</strong> can be assessed by trapping the animal in a readily recognized situation, then re-exposing the animal to the trap in the appropriate situation and evaluating its behaviour."},{"author":118293,"first":"Visceral <strong class=\"keyword\">aversión</strong> Toru Hyuga lo hace por el logro académ ico","second":"Toru Hyuga's visceral <strong class=\"keyword\">aversion</strong> for academic achievement"},{"author":118293,"first":"Gustos, <strong class=\"keyword\">aversiones</strong>, miedos, esperanzas, fotos, vídeos, pensamientos y deseos íntimos.","second":"Likes, <strong class=\"keyword\">dislikes</strong>, fears, hopes, photos, videos, intimate thoughts and desires."},{"author":94808,"first":"La delegación no dispone de estadísticas sobre los delitos de <strong class=\"keyword\">aversión</strong>, pero puede incluirlas en el quinto informe periódico.","second":"The delegation did not have any statistics on <strong class=\"keyword\">hate</strong> crimes, but could include them in the fifth periodic report."},{"author":95875,"first":"Entre los puntos débiles están su <strong class=\"keyword\">aversión</strong> al riesgo, la fragmentación de los mercados europeos, la baja movilidad de la mano de obra y la ausencia de sensación de urgencia.","second":"Weaknesses include a risk-<strong class=\"keyword\">averse</strong> mentality, fragmented European markets, low labour mobility, and a lack of urgency."},{"author":94808,"first":"Explicación de la <strong class=\"keyword\">aversión</strong> del Banco Mundial hacia los derechos humanos","second":"Explaining the <strong class=\"keyword\">aversion</strong> of the World Bank to human rights"},{"author":94809,"first":"En Europa, no sólo existen diferencias considerables en el nivel de capital riesgo disponible en cada Estado miembro, sino que habitualmente se observa una mayor <strong class=\"keyword\">aversión</strong> al riesgo, al tiempo que una gran proporción de los fondos disponibles se utiliza para financiar adquisiciones de empresas por sus propios ejecutivos o por ejecutivos ajenos a la misma en empresas consolidadas de tamaño considerable.","second":"In Europe, not only are there considerable differences in the level of venture capital available between Member States; it tends to be more risk <strong class=\"keyword\">averse</strong>, with a high proportion of available funds going to support Management Buy-Outs and Management Buy-Ins in well-established companies of fairly substantial size."},{"author":8000,"first":"\"[La islamofobia] consiste en una hostilidad infundada contra el islam y, por consiguiente, en un sentimiento de temor y de <strong class=\"keyword\">aversión</strong> respecto de todos los musulmanes o de la mayoría de éstos","second":"“[Islamophobia] refers to a baseless hostility and fear vis-à-vis Islam, and as a result a fear of and <strong class=\"keyword\">aversion towards</strong> all Muslims or the majority of them"},{"author":8000,"first":"También provoca deserción escolar, <strong class=\"keyword\">aversión</strong> al sexo y prostitución","second":"It also leads to school dropout, sexual <strong class=\"keyword\">aversion</strong>, and prostitution"},{"author":31,"first":"Esto es lo que se conoce como terapia de <strong class=\"keyword\">aversión</strong>","second":"This is what is known as <strong class=\"keyword\">aversion</strong> therapy"},{"author":42,"first":"respuestas de comportamiento tras la captura, incluyendo vocalizaciones, pánico extremo, plazo de tiempo transcurrido hasta la vuelta a un comportamiento normal tras la liberación de la trampa y la manifestación de <strong class=\"keyword\">aversión</strong>","second":"behavioural responses after trapping, including vocalisations, extreme panic, delay before return to normal behaviour after release from trap and <strong class=\"keyword\">aversiveness</strong>"},{"author":94808,"first":"En el sector público predominan los riesgos operacionales, la cultura es principalmente de <strong class=\"keyword\">aversión</strong> al riesgo y los encargados de la gestión del riesgo se ocupan de promover una asunción de riesgos responsable.","second":"In the public sector, operational risk is prevalent, the culture is mostly risk <strong class=\"keyword\">averse</strong>, and the risk management position is to promote responsible risk-taking."},{"author":94808,"first":"La Comisión hace notar las explicaciones y los análisis que se le proporcionaron, a petición suya, en relación con los factores de costos y los demás factores que determinan el nivel de la eficacia en función de los costos y la <strong class=\"keyword\">aversión</strong> a los riesgos de cada opción.","second":"The Committee notes the explanations and analysis provided to it, upon enquiry, concerning the cost drivers and the factors which determine the level of cost-effectiveness and risk-<strong class=\"keyword\">aversion</strong> of each option."},{"author":94809,"first":"228 Por su parte, la Comisión sostiene que la determinación del tipo mínimo es, en el presente caso, una operación que debe inscribirse en un contexto histórico determinado en función de una apreciación prospectiva, que tenga en cuenta el grado psicológico y subjetivo de propensión o <strong class=\"keyword\">aversión</strong> al riesgo en un sector concreto y tan interdependiente como el del transporte aéreo.","second":"228 The Commission submits that the determination of the minimum rate is, in the present case, an operation which must be viewed from a historical perspective, based on a prospective assessment taking into account the psychological and subjective degree of the propensity or <strong class=\"keyword\">aversion</strong> to risk in a particular sector which is as interdependent as the air transport sector."},{"author":92475,"first":"Comprensiblemente, las personas del usualmente tranquilo país reaccionaron con <strong class=\"keyword\">aversión</strong> y angustia, tal vez presintiendo una destrozada estructura social.","second":"Understandably, people in the usually tranquil country reacted with both <strong class=\"keyword\">loathing</strong> and anguish, perhaps as a premonition of a shattered social fabric."},{"author":22,"first":"Señala-y espera una respuesta al respecto- la cuestión de cómo ha podido desarrollarse una cultura de <strong class=\"keyword\">aversión</strong> al riesgo (relegando proyectos innovadores y de elevada calidad), práctica que se opone al objetivo comunitario definido en la Estrategia de Lisboa; considera que la financiación de inversiones en infraestructuras no constituye un problema, sino que ofrece a los Estados miembros la posibilidad de evitar inversiones innovadoras-es decir, de riesgo","second":"Points out- and seeks an answer to- the question of how the risk-<strong class=\"keyword\">averse</strong> culture might have come about (with high-quality, innovative investments losing prominence), a practice which runs completely counter to the Community’s efforts as laid down in the Lisbon Strategy; considers that the problem lies not with funding infrastructure investments but with the fact that Member States have the opportunity to avoid innovative- risky- investments"},{"author":118293,"first":"Esto nos enseña que este tipo de terapias pueden ser usadas Para curar <strong class=\"keyword\">aversiones</strong> similares Por ejemplo: miedo a la suciedad, excrementos e, incluso, cadáveres.","second":"This shows that this kind of therapy can be used... to cure other, similar <strong class=\"keyword\">aversions</strong>:"},{"author":31,"first":"Sentirían <strong class=\"keyword\">aversión</strong> y se alejarían de mi","second":"You' d feel <strong class=\"keyword\">aversion</strong> and walk away"},{"author":118293,"first":"Y Lucy nos devuelve gustos y <strong class=\"keyword\">aversiones</strong> de Dearing.","second":"And Lucy's telling us Dearing's likes and <strong class=\"keyword\">dislikes</strong>."},{"author":94809,"first":"Esa técnica es preferible a la inhalación de dióxido de carbono, que puede causar <strong class=\"keyword\">aversión</strong>.","second":"This is preferable to carbon dioxide inhalation, as carbon dioxide may be <strong class=\"keyword\">aversive</strong>."},{"author":31,"first":"Una mejor pregunta sería, ¿ qué pasaría si sigues con la historia y resulta que Croelick no tenía nada que ver con el incendio del Parque Griffith y te toma una <strong class=\"keyword\">aversión</strong> inmediata?","second":"A better question would be, what if you run the story and it turns out Croelick had nothing to do with the park fire and he takes an instant <strong class=\"keyword\">dislike</strong> to you?"},{"author":31,"first":"Mi <strong class=\"keyword\">aversión</strong> hacia Ios Estados Unidos es cosa deI pasado","second":"<strong class=\"keyword\">But</strong> then, it was a long time ago when I felt bitter about America"},{"author":31,"first":"Cuando paseo, me siento como con las botas de siete leguas, entiendo incluso tu <strong class=\"keyword\">aversión</strong> a la política, Wilhelm","second":"I feel like I had seven- league boots on.I even understand your <strong class=\"keyword\">revulsion against</strong> politics, Wilhelm"}],"from":"es","dest":"en","authors":{"80097":{"U":"http://www.btb.termiumplus.gc.ca/","id":80097,"N":"Termium","url":"https://glosbe.com/source/80097"},"8000":{"U":"http://opus.lingfil.uu.se/MultiUN.php","id":8000,"N":"MultiUn","url":"https://glosbe.com/source/8000"},"1":{"U":"http://en.wiktionary.org","id":1,"N":"en.wiktionary.org","url":"https://glosbe.com/source/1"},"95875":{"U":"http://cordis.europa.eu","id":95875,"N":"cordis","url":"https://glosbe.com/source/95875"},"36":{"U":"http://freedict.org","id":36,"N":"freedict.org","url":"https://glosbe.com/source/36"},"8":{"U":"http://es.wiktionary.org","id":8,"N":"es.wiktionary.org","url":"https://glosbe.com/source/8"},"9":{"U":"http://fr.wiktionary.org","id":9,"N":"fr.wiktionary.org","url":"https://glosbe.com/source/9"},"84715":{"U":"","id":84715,"N":"English—Spanish","url":"https://glosbe.com/source/84715"},"2698":{"U":"http://dumps.wikimedia.org/frwiktionary/latest/frwiktionary-latest-pages-articles.xml.bz2","id":2698,"N":"Wiktionnaire","url":"https://glosbe.com/source/2698"},"42":{"U":"http://eur-lex.europa.eu/","id":42,"N":"eurlex","url":"https://glosbe.com/source/42"},"60172":{"U":"http://www.omegawiki.org/","id":60172,"N":"omegawiki","url":"https://glosbe.com/source/60172"},"69425":{"U":"","id":69425,"N":"plwiktionary.org","url":"https://glosbe.com/source/69425"},"97745":{"U":"","id":97745,"N":"Glosbe-Trav-CDMultilang","url":"https://glosbe.com/source/97745"},"70195":{"U":"","id":70195,"N":"en.wiktionary.org_2014","url":"https://glosbe.com/source/70195"},"118293":{"U":"https://www.opensubtitles.org/","id":118293,"N":"opensubtitles2017","url":"https://glosbe.com/source/118293"},"84500":{"U":"","id":84500,"N":"Open Multilingual Wordnet","url":"https://glosbe.com/source/84500"},"22":{"U":"http://eur-lex.europa.eu/JOIndex.do","id":22,"N":"oj4","url":"https://glosbe.com/source/22"},"94809":{"U":"","id":94809,"N":"EurLex-2","url":"https://glosbe.com/source/94809"},"94808":{"U":"","id":94808,"N":"UN-2","url":"https://glosbe.com/source/94808"},"25018":{"U":"http://glosbe.com","id":25018,"N":"GlosbeResearch","url":"https://glosbe.com/source/25018"},"92475":{"U":"http://globalvoicesonline.org","id":92475,"N":"globalvoices","url":"https://glosbe.com/source/92475"},"31":{"U":"http://www.opensubtitles.org/","id":31,"N":"opensubtitles2","url":"https://glosbe.com/source/31"}}}