{"result":"ok","tuc":[{"phrase":{"text":"impertinent","language":"en"},"meanings":[{"language":"en","text":"Not showing due respect."},{"language":"es","text":"Que no muestra respeto."},{"language":"en","text":"insolent, ill-mannered"}],"meaningId":299256267058880133,"authors":[70195]},{"phrase":{"text":"sassy","language":"en"},"meanings":[{"language":"en","text":"Not showing due respect."},{"language":"es","text":"Que no muestra respeto."}],"meaningId":-6954676456673820141,"authors":[60172]},{"phrase":{"text":"snotty","language":"en"},"meanings":[{"language":"en","text":"ill-tempered, impertinent"}],"meaningId":-5071333628378771461,"authors":[70195]},{"phrase":{"text":"rude","language":"en"},"meaningId":-3081416946949286122,"authors":[89651]},{"phrase":{"text":"wrong","language":"en"},"meaningId":-461095606784424210,"authors":[69425]},{"phrase":{"text":"saucy","language":"en"},"meanings":[{"language":"en","text":"Not showing due respect."},{"language":"es","text":"Que no muestra respeto."}],"meaningId":-8800217496575000096,"authors":[60172]},{"phrase":{"text":"smart","language":"en"},"meanings":[{"language":"en","text":"Not showing due respect."},{"language":"es","text":"Que no muestra respeto."}],"meaningId":-1776706385416555805,"authors":[83619]},{"phrase":{"text":"wise","language":"en"},"meanings":[{"language":"en","text":"Not showing due respect."},{"language":"es","text":"Que no muestra respeto."}],"meaningId":-2807131603159838423,"authors":[83619]},{"phrase":{"text":"bold","language":"en"},"meaningId":-3962911169093261816,"authors":[2698]},{"phrase":{"text":"callous","language":"en"},"meaningId":5918228252827446772,"authors":[2697]},{"phrase":{"text":"cheeky","language":"en"},"meaningId":-1978337074213199798,"authors":[25018]},{"phrase":{"text":"flippant","language":"en"},"meaningId":4395804743736690669,"authors":[89651]},{"phrase":{"text":"brazen-faced","language":"en"},"meanings":[{"language":"en","text":"Not showing due respect."},{"language":"es","text":"Que no muestra respeto."}],"meaningId":-2336581099074171268,"authors":[60172]},{"phrase":{"text":"fresh","language":"en"},"meanings":[{"language":"en","text":"Not showing due respect."},{"language":"es","text":"Que no muestra respeto."}],"meaningId":-7840393704571097361,"authors":[60172]},{"phrase":{"text":"impudent","language":"en"},"meanings":[{"language":"en","text":"Not showing due respect."},{"language":"es","text":"Que no muestra respeto."}],"meaningId":-533892632826978365,"authors":[60172]},{"phrase":{"text":"overbold","language":"en"},"meanings":[{"language":"en","text":"Not showing due respect."},{"language":"es","text":"Que no muestra respeto."}],"meaningId":-690493157654316359,"authors":[60172]},{"phrase":{"text":"audacious","language":"en"},"meaningId":-4969240713012066468,"authors":[2698]},{"phrase":{"text":"blatant","language":"en"},"meaningId":-3995199363239870492,"authors":[83042]},{"phrase":{"text":"brash","language":"en"},"meaningId":5881408519537734640,"authors":[97745]},{"phrase":{"text":"brazen","language":"en"},"meaningId":6714516845616840600,"authors":[2698]},{"phrase":{"text":"daring","language":"en"},"meaningId":-5794611693372725541,"authors":[2698]},{"phrase":{"text":"fearless","language":"en"},"meaningId":-4369265679026978620,"authors":[2698]},{"phrase":{"text":"impertinent person","language":"en"},"meaningId":-4749583847931424026,"authors":[83086]},{"phrase":{"text":"intrusive","language":"en"},"meaningId":-3410640568858950171,"authors":[25018]},{"phrase":{"text":"irrelevant","language":"en"},"meaningId":8839878591715966813,"authors":[25018]},{"phrase":{"text":"meddlesome","language":"en"},"meaningId":7802300565643588379,"authors":[83042]},{"phrase":{"text":"perky","language":"en"},"meaningId":-1043306464199493794,"authors":[2698]},{"phrase":{"text":"pert","language":"en"},"meaningId":620905189998213373,"authors":[25018]},{"phrase":{"text":"presumptuous","language":"en"},"meaningId":7067684559738094329,"authors":[97745]},{"phrase":{"text":"uncalled-for","language":"en"},"meaningId":1855161064973363544,"authors":[97745]},{"phrase":{"text":"unflinching","language":"en"},"meaningId":-1448917204039159028,"authors":[2698]},{"meanings":[{"language":"en","text":"impertinent, cheeky"}],"meaningId":404603297261306315,"authors":[93107]}],"phrase":"impertinente","examples":[{"author":31,"first":"Se considera <strong class=\"keyword\">impertinente</strong>","second":"It' <strong class=\"keyword\">s</strong> considered <strong class=\"keyword\">gauche</strong>"},{"author":118293,"first":"No importa lo que diga, Señor Watts, siempre es un <strong class=\"keyword\">impertinente</strong>.","second":"Doesn't care what he says, Mr Watts. Always <strong class=\"keyword\">cheeky!</strong>"},{"author":8000,"first":"El Gobierno rechaza esas críticas por ser infundadas e <strong class=\"keyword\">impertinentes</strong>","second":"The Government rejects this criticism as unfounded and <strong class=\"keyword\">derogatory</strong>"},{"author":89915,"first":"Gafas [óptica], Gafas de sol, Anteojos antirreflejo, Gafas protectoras para deporte, Cristales para gafas, Estuches para gafas, Monóculos, Binoculares, Gemelos de teatro, Monturas de gafas, Monturas de <strong class=\"keyword\">impertinentes</strong>, Lentes de contacto, Estuches para lentes de contacto, Partes, Estuches, Cordones, Cristales intercambiables y componentes para gafas y gafas de sol","second":"Spectacles [optics], Sunglasses, Anti-glare glasses, Goggles for sports, Lenses for eyeglasses, Glasses cases, Monocles, Binoculars, Theatre glasses, Frames for glasses, <strong class=\"keyword\">Lorgnette</strong> frames, Contact lenses, Containers for contact lenses, parts, Cases, cords, Exchangeable lenses and components for spectacles and sunglasses"},{"author":94809,"first":"19 La Comisión, sin responder directamente a la cuestión planteada, que considera <strong class=\"keyword\">impertinente</strong>, señala que la Administración tributaria del Reino Unido interpretó erróneamente la legislación nacional, pero que no infringió ninguna obligación establecida en la Sexta Directiva.","second":"19 The Commission, without replying directly to the question, which it regards as <strong class=\"keyword\">irrelevant</strong>, states that the United Kingdom tax authorities were mistaken in their interpretation of the national legislation, but did not breach any obligation imposed by the Sixth Directive."},{"author":118293,"first":"Les parecerá que soy demasiado <strong class=\"keyword\">impertinente</strong>.","second":"Probably regard it as pretty nervy of <strong class=\"keyword\">me</strong>."},{"author":31,"first":"<strong class=\"keyword\">Impertinente</strong> y maldito judío","second":"<strong class=\"keyword\">You impertinent</strong>, filthy Jew"},{"author":118293,"first":"¡ Es usted un <strong class=\"keyword\">impertinente</strong>!","second":"What blasted <strong class=\"keyword\">impertinence</strong>."},{"author":119739,"first":"Por lo general se estima <strong class=\"keyword\">impertinente</strong> que los jóvenes llamen a los adultos por su nombre de pila, a menos que se les haya permitido hacerlo.","second":"It is generally viewed as <strong class=\"keyword\">impertinent</strong> for youths to call adults by their first name unless the youths receive permission to do so."},{"author":118293,"first":"No queremos ser <strong class=\"keyword\">impertinentes</strong>, señor.","second":"We don't mean no <strong class=\"keyword\">impertinence</strong>, sir."},{"author":94808,"first":"El Tribunal Contencioso-Administrativo podrá excluir las pruebas que considere <strong class=\"keyword\">impertinentes</strong>, inútiles o carentes de valor probatorio.","second":"The Dispute Tribunal may exclude evidence which it considers <strong class=\"keyword\">irrelevant</strong>, <strong class=\"keyword\">frivolous</strong> or lacking in probative value."},{"author":27,"first":"No obstante, la conducta provocadora de Turquía se ha manifestado también después de Imia, con amenazas bélicas, con declaraciones descabelladas de algunos ministros, con reivindicaciones <strong class=\"keyword\">impertinentes</strong> y con impugnaciones de la soberanía de determinados miembros de la Unión Europea.","second":"However, Turkey has been stirring up trouble even since Imia. There have been threats of war, frenzied statements by ministers, <strong class=\"keyword\">brazen</strong> territorial claims and aspersions about the sovereignty of Members of the Union."},{"author":118293,"first":"Es Vd. <strong class=\"keyword\">Impertinente</strong>.","second":"Are you <strong class=\"keyword\">being impudent?</strong>"},{"author":118293,"first":"Fue muy <strong class=\"keyword\">impertinente</strong> y me hizo no querer estar aquí así que...","second":"It was so <strong class=\"keyword\">intrusive</strong>, and it made me not want to be here, so, that's-"},{"author":118293,"first":"¿Siempre es tan <strong class=\"keyword\">impertinente</strong>?","second":"Are you always so <strong class=\"keyword\">impertinent</strong>?"},{"author":118293,"first":"Ésa fue una pregunta <strong class=\"keyword\">impertinente</strong>.","second":"That would be none of <strong class=\"keyword\">my</strong> business."},{"author":31,"first":"La petición es \" <strong class=\"keyword\">impertinente</strong> \" a mí, como sabréis por este honrado anciano, un hombre anciano, un pobre hombre, mi padre","second":"In very brief, the suit is <strong class=\"keyword\">impertinent</strong> to myself, as your worship shall know by this honest old man.And, though I say it, though old man, yet poor man, my father"},{"author":31,"first":"¿ Está intentando ser <strong class=\"keyword\">impertinente</strong>?","second":"Are you trying to be <strong class=\"keyword\">impertinent</strong>?"},{"author":118293,"first":"¡ Qué <strong class=\"keyword\">impertinente</strong>!","second":"The <strong class=\"keyword\">cheeky</strong> bastard!"},{"author":8008,"first":"Y la pregunta <strong class=\"keyword\">impertinente</strong>, podría Carlos Sainz destacar en estos momentos sobre Loeb?","second":"Tiña pensado poñer un video do campeonato do mund, pero xa que o <strong class=\"keyword\">coñezo</strong>, é vive máis preto de min poño éste de Cesar Gonzalves(Porto), veciño e colega, no tramo de Narahio, rallye cidade de Narón 2006."},{"author":118293,"first":"Su comportamiento me parece muy <strong class=\"keyword\">impertinente</strong> \".","second":"I consider your behavior a <strong class=\"keyword\">deliberate impertinence</strong>. \""},{"author":118293,"first":"No seas tan condenadamente <strong class=\"keyword\">impertinente</strong>.","second":"Don't be so damned impertin ent<strong class=\"keyword\">!</strong>"},{"author":31,"first":"Primero:Eso es muy <strong class=\"keyword\">impertinente</strong> de tu parte","second":"And I<strong class=\"keyword\">'</strong> m the sex column they run next to ads for penile implants"},{"author":118293,"first":"Yo soy la <strong class=\"keyword\">impertinente</strong>.","second":"The presumption's all <strong class=\"keyword\">mine</strong>."},{"author":118293,"first":"Murmurando cuando, la enfermera jefe, te habla, eres rebelde e <strong class=\"keyword\">impertinente</strong>, y eso se refleja en todas nosotras.","second":"Muttering under your breath when Matron's speaking to you, being defiant and <strong class=\"keyword\">impertinent</strong> - well, it reflects on all of us."}],"from":"es","dest":"en","authors":{"8000":{"U":"http://opus.lingfil.uu.se/MultiUN.php","id":8000,"N":"MultiUn","url":"https://glosbe.com/source/8000"},"83619":{"U":"","id":83619,"N":"Common U++ UNL Dictionary","url":"https://glosbe.com/source/83619"},"83042":{"U":"","id":83042,"N":"Dbnary: Wiktionary as Linguistic Linked Open Data","url":"https://glosbe.com/source/83042"},"8008":{"U":"http://www.statmt.org/wmt13/translation-task.html","id":8008,"N":"Common crawl","url":"https://glosbe.com/source/8008"},"2697":{"U":"http://dumps.wikimedia.org/dewiktionary/latest/dewiktionary-latest-pages-articles.xml.bz2","id":2697,"N":"Wikiworterbuch","url":"https://glosbe.com/source/2697"},"2698":{"U":"http://dumps.wikimedia.org/frwiktionary/latest/frwiktionary-latest-pages-articles.xml.bz2","id":2698,"N":"Wiktionnaire","url":"https://glosbe.com/source/2698"},"60172":{"U":"http://www.omegawiki.org/","id":60172,"N":"omegawiki","url":"https://glosbe.com/source/60172"},"83086":{"U":"","id":83086,"N":"Dbnary: Wiktionary as Linguistic Linked Open Data","url":"https://glosbe.com/source/83086"},"69425":{"U":"","id":69425,"N":"plwiktionary.org","url":"https://glosbe.com/source/69425"},"97745":{"U":"","id":97745,"N":"Glosbe-Trav-CDMultilang","url":"https://glosbe.com/source/97745"},"70195":{"U":"","id":70195,"N":"en.wiktionary.org_2014","url":"https://glosbe.com/source/70195"},"89651":{"U":"","id":89651,"N":"GlosbeWordalignmentRnD","url":"https://glosbe.com/source/89651"},"93107":{"U":"","id":93107,"N":"enwiki-01-2017-defs","url":"https://glosbe.com/source/93107"},"118293":{"U":"https://www.opensubtitles.org/","id":118293,"N":"opensubtitles2017","url":"https://glosbe.com/source/118293"},"94809":{"U":"","id":94809,"N":"EurLex-2","url":"https://glosbe.com/source/94809"},"94808":{"U":"","id":94808,"N":"UN-2","url":"https://glosbe.com/source/94808"},"25018":{"U":"http://glosbe.com","id":25018,"N":"GlosbeResearch","url":"https://glosbe.com/source/25018"},"89915":{"U":"http://tmclass.tmdn.org/","id":89915,"N":"tmClass","url":"https://glosbe.com/source/89915"},"119739":{"U":"","id":119739,"N":"JW_2017_12","url":"https://glosbe.com/source/119739"},"27":{"U":"http://www.statmt.org/europarl/","id":27,"N":"Europarl8","url":"https://glosbe.com/source/27"},"31":{"U":"http://www.opensubtitles.org/","id":31,"N":"opensubtitles2","url":"https://glosbe.com/source/31"}}}